ocrrouter/__init__.py
ocrrouter/version.py
ocrrouter/backends/__init__.py
ocrrouter/backends/factory.py
ocrrouter/backends/models/__init__.py
ocrrouter/backends/models/base/__init__.py
ocrrouter/backends/models/base/backend.py
ocrrouter/backends/models/base/client.py
ocrrouter/backends/models/base/postprocessor.py
ocrrouter/backends/models/base/preprocessor.py
ocrrouter/backends/models/composite/__init__.py
ocrrouter/backends/models/composite/backend.py
ocrrouter/backends/models/composite/client.py
ocrrouter/backends/models/deepseek/__init__.py
ocrrouter/backends/models/deepseek/backend.py
ocrrouter/backends/models/deepseek/client.py
ocrrouter/backends/models/deepseek/postprocessor.py
ocrrouter/backends/models/deepseek/preprocessor.py
ocrrouter/backends/models/deepseek/utils/__init__.py
ocrrouter/backends/models/deepseek/utils/structs.py
ocrrouter/backends/models/dotsocr/__init__.py
ocrrouter/backends/models/dotsocr/backend.py
ocrrouter/backends/models/dotsocr/client.py
ocrrouter/backends/models/dotsocr/postprocessor.py
ocrrouter/backends/models/dotsocr/preprocessor.py
ocrrouter/backends/models/dotsocr/utils/__init__.py
ocrrouter/backends/models/dotsocr/utils/structs.py
ocrrouter/backends/models/generalvlm/__init__.py
ocrrouter/backends/models/generalvlm/backend.py
ocrrouter/backends/models/generalvlm/client.py
ocrrouter/backends/models/generalvlm/postprocessor.py
ocrrouter/backends/models/generalvlm/preprocessor.py
ocrrouter/backends/models/hunyuanocr/__init__.py
ocrrouter/backends/models/hunyuanocr/backend.py
ocrrouter/backends/models/hunyuanocr/client.py
ocrrouter/backends/models/hunyuanocr/postprocessor.py
ocrrouter/backends/models/hunyuanocr/preprocessor.py
ocrrouter/backends/models/mineru/__init__.py
ocrrouter/backends/models/mineru/backend.py
ocrrouter/backends/models/mineru/client.py
ocrrouter/backends/models/mineru/postprocessor.py
ocrrouter/backends/models/mineru/preprocessor.py
ocrrouter/backends/models/mineru/post_process/__init__.py
ocrrouter-0.1.3.dist-info/licenses/LICENSE
ocrrouter-0.1.3.dist-info/METADATA
ocrrouter-0.1.3.dist-info/WHEEL
ocrrouter-0.1.3.dist-info/top_level.txt
ocrrouter-0.1.3.dist-info/RECORD
