Metadata-Version: 2.4
Name: ocrrouter
Version: 0.1.3
Summary: A practical tool for converting PDF to Markdown
Author-email: Tan Jun An <jun.an@n1.healthcare>
License-Expression: AGPL-3.0
Project-URL: Homepage, https://github.com/n1healthcare/OcrRouter
Project-URL: Repository, https://github.com/n1healthcare/OcrRouter
Project-URL: Issues, https://github.com/n1healthcare/OcrRouter/issues
Project-URL: Documentation, https://github.com/n1healthcare/OcrRouter#readme
Keywords: magic-pdf,convert,pdf,markdown,ocr,router
Classifier: Programming Language :: Python :: 3.10
Classifier: Programming Language :: Python :: 3.11
Classifier: Programming Language :: Python :: 3.12
Classifier: Programming Language :: Python :: 3.13
Requires-Python: <3.14,>=3.10
License-File: LICENSE
Requires-Dist: loguru>=0.7.2
Requires-Dist: numpy>=1.21.6
Requires-Dist: tqdm>=4.67.1
Requires-Dist: requests
Requires-Dist: httpx
Requires-Dist: pillow>=11.0.0
Requires-Dist: pypdfium2>=4.30.0
Requires-Dist: pypdf>=5.6.0
Requires-Dist: reportlab
Requires-Dist: beautifulsoup4<5,>=4.13.5
Requires-Dist: magika<1.1.0,>=0.6.2
Requires-Dist: langchain-openai>=0.3.0
Requires-Dist: langchain-core>=0.3.0
Requires-Dist: packaging>=21.0
Requires-Dist: aiofiles>=25.1.0
Requires-Dist: pydantic-settings>=2.12.0
Requires-Dist: langfuse>=3.11.1
Requires-Dist: langchain>=1.2.0
Provides-Extra: dev
Requires-Dist: ipykernel>=7.1.0; extra == "dev"
Dynamic: license-file
